{
  "footer__linkki_avautuu_uuteen_ikkunaan": "Link opens in a new window",
  "footer__palaute": "Report an error or give feedback",
  "footer__tietoa_tunnistautumisesta": "Information about Suomi.fi-identification",
  "footer__tietosuojaseloste": "Description of file in compliance with the Personal Data Act",
  "footer__tunnistuspalvelusta_vastaa": "Suomi.fi identification is the responsibility of the",
  "footer__vaestorekisterikeskus": "Population Register Centre",
  "footer__vrk_url": "http://vrk.fi/en",
  "testword": "EN_kala"
}